w32_fnmatch/__init__.py
w32_fnmatch-1.1.dist-info/METADATA
w32_fnmatch-1.1.dist-info/WHEEL
w32_fnmatch-1.1.dist-info/top_level.txt
w32_fnmatch-1.1.dist-info/RECORD
